rag_mcp/__init__.py
rag_mcp/document_server.py
rag_mcp-0.1.4.dist-info/METADATA
rag_mcp-0.1.4.dist-info/WHEEL
rag_mcp-0.1.4.dist-info/entry_points.txt
rag_mcp-0.1.4.dist-info/top_level.txt
rag_mcp-0.1.4.dist-info/RECORD
